{
  "history": [
    {
      "type": "upload",
      "accountId": "3f858412-2fbf-433d-9cc7-f0546499c2f0",
      "accountUsername": "uzzatoday",
      "content": "너무 감동이다",
      "hasImage": true,
      "status": "success",
      "mediaId": "18286748062304357",
      "timestamp": "2026-03-17T12:17:15.712Z"
    },
    {
      "type": "upload",
      "accountId": "3f858412-2fbf-433d-9cc7-f0546499c2f0",
      "accountUsername": "uzzatoday",
      "content": "여자들이 1순위로 보는 남자 조건",
      "hasImage": true,
      "status": "success",
      "mediaId": "17867235087597172",
      "timestamp": "2026-03-17T10:43:19.666Z"
    },
    {
      "type": "upload",
      "accountId": "3f858412-2fbf-433d-9cc7-f0546499c2f0",
      "accountUsername": "uzzatoday",
      "content": "와... 진짜 존경스럽다… 👍",
      "hasImage": true,
      "status": "success",
      "mediaId": "18178770322343392",
      "timestamp": "2026-03-17T10:42:46.115Z"
    },
    {
      "type": "upload",
      "accountId": "3f858412-2fbf-433d-9cc7-f0546499c2f0",
      "accountUsername": "uzzatoday",
      "content": "여자들이 1순위로 보는 남자 조건",
      "hasImage": true,
      "status": "success",
      "mediaId": "17945837081983625",
      "timestamp": "2026-03-17T10:42:34.542Z"
    },
    {
      "type": "upload",
      "accountId": "3f858412-2fbf-433d-9cc7-f0546499c2f0",
      "accountUsername": "uzzatoday",
      "content": "와... 진짜 존경스럽다… 👍",
      "hasImage": true,
      "status": "success",
      "mediaId": "18114721198735460",
      "timestamp": "2026-03-17T10:41:56.896Z"
    },
    {
      "type": "upload",
      "accountId": "e335a502-ec69-4266-a517-1b0c29a248e7",
      "accountUsername": "battleofwin45",
      "content": "[Gemini Pro 패치 테스트] dayjs 타임존 및 Rebase 로직 적용 후 업로드 테스트입니다. (등록시간: 2026. 3. 16. PM 9:04:51)",
      "hasImage": true,
      "status": "success",
      "mediaId": "18113697079593855",
      "timestamp": "2026-03-16T12:50:25.769Z"
    },
    {
      "type": "upload",
      "accountId": "e335a502-ec69-4266-a517-1b0c29a248e7",
      "accountUsername": "battleofwin45",
      "content": "[최종 GHA 테스트] 토큰 동기화 패치 후 서버 OFF 예약 업로드 테스트입니다. (등록시간: 2026. 3. 16. PM 8:59:11)",
      "hasImage": true,
      "status": "success",
      "mediaId": "18561967909051244",
      "timestamp": "2026-03-16T12:50:12.140Z"
    },
    {
      "type": "upload",
      "accountId": "e335a502-ec69-4266-a517-1b0c29a248e7",
      "accountUsername": "battleofwin45",
      "content": "[디버깅 테스트] 서버 OFF 환경 예약 업로드 테스트입니다. (등록시간: 2026. 3. 16. PM 8:19:43, 예약시간: 2026-03-16T20:45)",
      "hasImage": true,
      "status": "success",
      "mediaId": "18076905857625896",
      "timestamp": "2026-03-16T11:57:46.240Z"
    },
    {
      "type": "upload",
      "accountId": "3f858412-2fbf-433d-9cc7-f0546499c2f0",
      "accountUsername": "uzzatoday",
      "content": "앜ㅋㅋㅋㅋㅋ 마지막 반전 뭔데요 🤣",
      "hasImage": true,
      "status": "success",
      "mediaId": "18194127418358735",
      "timestamp": "2026-03-16T10:56:07.382Z"
    },
    {
      "type": "upload",
      "accountId": "e335a502-ec69-4266-a517-1b0c29a248e7",
      "accountUsername": "battleofwin45",
      "content": "중국 성형수술...",
      "hasImage": true,
      "status": "success",
      "mediaId": "18109846690705032",
      "timestamp": "2026-03-15T12:33:49.618Z"
    },
    {
      "type": "upload",
      "accountId": "e335a502-ec69-4266-a517-1b0c29a248e7",
      "accountUsername": "battleofwin45",
      "content": "중국 성형수술...",
      "hasImage": true,
      "status": "failed",
      "error": "An unexpected error has occurred. Please retry your request later.",
      "timestamp": "2026-03-15T12:32:17.736Z"
    },
    {
      "type": "upload",
      "accountId": "3f858412-2fbf-433d-9cc7-f0546499c2f0",
      "accountUsername": "uzzatoday",
      "content": "이광수 쉿이 나온 이유 ㅋㅋ",
      "hasImage": true,
      "status": "success",
      "mediaId": "17934746022190987",
      "timestamp": "2026-03-15T10:38:46.371Z"
    },
    {
      "type": "upload",
      "accountId": "3f858412-2fbf-433d-9cc7-f0546499c2f0",
      "accountUsername": "uzzatoday",
      "content": "이광수 쉿이 나온 이유 ㅋㅋ",
      "hasImage": true,
      "status": "failed",
      "error": "미디어 처리 대기 시간이 초과되었습니다.",
      "timestamp": "2026-03-15T10:33:53.309Z"
    },
    {
      "type": "upload",
      "accountId": "3f858412-2fbf-433d-9cc7-f0546499c2f0",
      "accountUsername": "uzzatoday",
      "content": "광기의 초보운전 ㄷㄷ",
      "hasImage": true,
      "status": "success",
      "mediaId": "18083267972249142",
      "timestamp": "2026-03-15T06:45:02.536Z"
    },
    {
      "type": "upload",
      "accountId": "3f858412-2fbf-433d-9cc7-f0546499c2f0",
      "accountUsername": "uzzatoday",
      "content": "아들 생각에 무너지는 아버지 마음 🥲... 시설 찾는 게 하늘의 별 따기라니 😥.",
      "hasImage": true,
      "status": "failed",
      "error": "미디어 처리 대기 시간이 초과되었습니다.",
      "timestamp": "2026-03-15T06:22:00.749Z"
    },
    {
      "type": "upload",
      "accountId": "e335a502-ec69-4266-a517-1b0c29a248e7",
      "accountUsername": "battleofwin45",
      "content": "아니… 헤어진 아빠 목소리에 저렇게 맘 아파하는 강아지가 어딨어 😭😭😭 진짜 눈물 왈칵 쏟아짐… 댕댕이들 순수함에 매번 감동받는다 🥺 우리 집 댕댕이한테도 영상 보여줘 봐야지… 반응 궁금해 🥰 이런 영상은 무조건 저장 각! #강아지 #댕댕이 #눈물주의",
      "hasImage": true,
      "status": "success",
      "mediaId": "18023822912805013",
      "timestamp": "2026-03-15T06:16:48.594Z"
    },
    {
      "type": "upload",
      "accountId": "e335a502-ec69-4266-a517-1b0c29a248e7",
      "accountUsername": "battleofwin45",
      "content": "아니 댕댕이 무슨 일이야ㅠㅠ 아빠 목소리에 저렇게 맘 아파하는 거 보니까 맴찢... 얼마나 보고 싶었을까😭 강아지 눈망울이 모든 걸 말해준다... 이런 영상 보면 괜히 울컥해🥺 나중에 우리 강아지한테 더 잘해야지! 🐶💖 \n\n#강아지 #눈물 #감동 #댕댕이 #일상",
      "hasImage": true,
      "status": "failed",
      "error": "미디어 처리 대기 시간이 초과되었습니다.",
      "timestamp": "2026-03-15T06:16:07.256Z"
    },
    {
      "type": "upload",
      "accountId": "3f858412-2fbf-433d-9cc7-f0546499c2f0",
      "accountUsername": "uzzatoday",
      "content": "ㅋㅋㅋㅋㅋ 나만 웃긴가? 🤣",
      "hasImage": true,
      "status": "failed",
      "error": "미디어 처리 대기 시간이 초과되었습니다.",
      "timestamp": "2026-03-15T05:46:54.306Z"
    },
    {
      "type": "upload",
      "accountId": "3f858412-2fbf-433d-9cc7-f0546499c2f0",
      "accountUsername": "uzzatoday",
      "content": "홍석천이 고무신이된 이유",
      "hasImage": true,
      "status": "success",
      "mediaId": "18157138672381943",
      "timestamp": "2026-03-14T11:54:26.018Z"
    },
    {
      "type": "reply",
      "accountId": "e335a502-ec69-4266-a517-1b0c29a248e7",
      "accountUsername": "battleofwin45",
      "content": "🔗 자세한 정보 보기\nhttps://search.shopping.naver.com/catalog/53903545069",
      "parentThreadId": "17942760936140732",
      "status": "success",
      "replyId": "18514983208074635",
      "timestamp": "2026-03-06T12:12:38.317Z"
    },
    {
      "type": "upload",
      "accountId": "e335a502-ec69-4266-a517-1b0c29a248e7",
      "accountUsername": "battleofwin45",
      "content": "요즘 미니멀리즘에 푹 빠져서 이것저것 정리 중인데, 책상 위 덩치 큰 가습기가 제일 거슬리더라고요. 🥲 그래서 큰맘 먹고 바꿨는데, 삶의 질이 달라졌어요. 바로 비브르 가습기! 디자인이 깔끔해서 어디에 둬도 찰떡이고, 무엇보다 가습량이 어마어마해요. 💨\n\n전에 쓰던 건 틀어도 건조했는데, 이건 틀자마자 촉촉함이 느껴져요. 밤새 틀어도 물 보충 걱정 없고",
      "hasImage": true,
      "status": "success",
      "mediaId": "17942760936140732",
      "timestamp": "2026-03-06T12:12:24.470Z"
    },
    {
      "type": "reply",
      "accountId": "e335a502-ec69-4266-a517-1b0c29a248e7",
      "accountUsername": "battleofwin45",
      "content": "🔗 자세한 정보 보기\nhttps://search.shopping.naver.com/catalog/53903594773",
      "parentThreadId": "18093740600091538",
      "status": "success",
      "replyId": "18093591907996087",
      "timestamp": "2026-03-06T12:12:06.237Z"
    },
    {
      "type": "upload",
      "accountId": "e335a502-ec69-4266-a517-1b0c29a248e7",
      "accountUsername": "battleofwin45",
      "content": "요즘 서류 작업할 때마다 어깨가 너무 아팠는데, 드디어 해방! ✨ 비브르 V31000 네이비 쓰고 완전 신세계 경험 중이에요. 디자인도 깔끔해서 사무실 분위기랑 찰떡이고, 무엇보다 장시간 앉아있어도 허리가 너무 편안해요.\n\n이거 쓰고 나서 집중력이 훨씬 높아졌다는 거! 🚀 생산성 향상은 말할 것도 없고요. 예전엔 퇴근하면 녹초였는데, 요즘은 운동도 거뜬히",
      "hasImage": true,
      "status": "success",
      "mediaId": "18093740600091538",
      "timestamp": "2026-03-06T12:11:54.505Z"
    },
    {
      "type": "reply",
      "accountId": "e335a502-ec69-4266-a517-1b0c29a248e7",
      "accountUsername": "battleofwin45",
      "content": "🔗 자세한 정보 보기\nhttps://smartstore.naver.com/main/products/11901197610",
      "parentThreadId": "17964931713040773",
      "status": "failed",
      "error": "The requested resource does not exist",
      "timestamp": "2026-03-06T12:11:34.861Z"
    },
    {
      "type": "upload",
      "accountId": "e335a502-ec69-4266-a517-1b0c29a248e7",
      "accountUsername": "battleofwin45",
      "content": "집 청소, 이제 진짜 스마트하게🧹!\n\n요즘 제가 푹 빠져있는 청소템은 바로 클래파 초경량 무선 청소기예요. '가벼운'이라는 단어가 찰떡! 손목에 무리 없이 슥슥 밀고 다니기 너무 좋아요.\n\n특히 자동 먼지 비움 기능은 혁신✨. 먼지통 비울 때마다 💨 날리는 미세먼지 걱정 싹 사라졌어요. 원룸처럼 좁은 공간에 딱!\n\n물걸레 키트까지 더하면 청소 시간 순삭",
      "hasImage": true,
      "status": "success",
      "mediaId": "17964931713040773",
      "timestamp": "2026-03-06T12:11:30.092Z"
    },
    {
      "type": "upload",
      "accountId": "e335a502-ec69-4266-a517-1b0c29a248e7",
      "accountUsername": "battleofwin45",
      "content": "음, 콘텐츠가 없으니 제가 임의로 하나 만들어볼게요! 😉\n\n**스레드 게시물 예시:**\n\n제목: 갓생 살고 싶어? 5분 안에 끝내는 아침 루틴 ✨\n\n본문:\n\n아침에 눈 뜨는 게 세상에서 제일 힘든 사람🙋‍♀️ (저요!) 5분 만에 갓생력 풀파워 충전하는 꿀팁 대방출!\n\n1️⃣ **기지개 쫙!**: 온몸 구석구석 잠 깨우기. 뇌에도 산소 공급 뿜뿜!\n2️",
      "hasImage": false,
      "status": "failed",
      "error": "API access blocked.",
      "timestamp": "2026-03-06T11:48:30.840Z"
    },
    {
      "type": "upload",
      "accountId": "e335a502-ec69-4266-a517-1b0c29a248e7",
      "accountUsername": "battleofwin45",
      "content": "음, 콘텐츠가 없으니 제가 임의로 하나 만들어볼게요! 😉\n\n**스레드 게시물 예시:**\n\n제목: 갓생 살고 싶어? 5분 안에 끝내는 아침 루틴 ✨\n\n본문:\n\n아침에 눈 뜨는 게 세상에서 제일 힘든 사람🙋‍♀️ (저요!) 5분 만에 갓생력 풀파워 충전하는 꿀팁 대방출!\n\n1️⃣ **기지개 쫙!**: 온몸 구석구석 잠 깨우기. 뇌에도 산소 공급 뿜뿜!\n2️",
      "hasImage": false,
      "status": "failed",
      "error": "API access blocked.",
      "timestamp": "2026-03-06T11:48:20.525Z"
    },
    {
      "type": "upload",
      "accountId": "e335a502-ec69-4266-a517-1b0c29a248e7",
      "accountUsername": "battleofwin45",
      "content": "음, 콘텐츠가 없으니 제가 임의로 하나 만들어볼게요! 😉\n\n**스레드 게시물 예시:**\n\n제목: 갓생 살고 싶어? 5분 안에 끝내는 아침 루틴 ✨\n\n본문:\n\n아침에 눈 뜨는 게 세상에서 제일 힘든 사람🙋‍♀️ (저요!) 5분 만에 갓생력 풀파워 충전하는 꿀팁 대방출!\n\n1️⃣ **기지개 쫙!**: 온몸 구석구석 잠 깨우기. 뇌에도 산소 공급 뿜뿜!\n2️",
      "hasImage": false,
      "status": "failed",
      "error": "API access blocked.",
      "timestamp": "2026-03-06T11:48:11.930Z"
    },
    {
      "type": "upload",
      "accountId": "e335a502-ec69-4266-a517-1b0c29a248e7",
      "accountUsername": "battleofwin45",
      "content": "음, 콘텐츠가 없으니 제가 임의로 하나 만들어볼게요! 😉\n\n**스레드 게시물 예시:**\n\n제목: 갓생 살고 싶어? 5분 안에 끝내는 아침 루틴 ✨\n\n본문:\n\n아침에 눈 뜨는 게 세상에서 제일 힘든 사람🙋‍♀️ (저요!) 5분 만에 갓생력 풀파워 충전하는 꿀팁 대방출!\n\n1️⃣ **기지개 쫙!**: 온몸 구석구석 잠 깨우기. 뇌에도 산소 공급 뿜뿜!\n2️",
      "hasImage": false,
      "status": "failed",
      "error": "API access blocked.",
      "timestamp": "2026-03-06T11:48:07.881Z"
    },
    {
      "type": "upload",
      "accountId": "e335a502-ec69-4266-a517-1b0c29a248e7",
      "accountUsername": "battleofwin45",
      "content": "음, 콘텐츠가 없으니 제가 임의로 하나 만들어볼게요! 😉\n\n**스레드 게시물 예시:**\n\n제목: 갓생 살고 싶어? 5분 안에 끝내는 아침 루틴 ✨\n\n본문:\n\n아침에 눈 뜨는 게 세상에서 제일 힘든 사람🙋‍♀️ (저요!) 5분 만에 갓생력 풀파워 충전하는 꿀팁 대방출!\n\n1️⃣ **기지개 쫙!**: 온몸 구석구석 잠 깨우기. 뇌에도 산소 공급 뿜뿜!\n2️",
      "hasImage": false,
      "status": "failed",
      "error": "API access blocked.",
      "timestamp": "2026-03-06T11:47:45.185Z"
    },
    {
      "type": "upload",
      "accountId": "e335a502-ec69-4266-a517-1b0c29a248e7",
      "accountUsername": "battleofwin45",
      "content": "반가워요",
      "hasImage": false,
      "status": "success",
      "mediaId": "18219440170313788",
      "timestamp": "2026-03-05T09:26:05.413Z"
    }
  ]
}